[
  {
    "Id": 314924,
    "GameId": 432,
    "Name": " 101 Dimensions",
    "Slug": "hundred-one-dimensions",
    "Summary": "A mod that adds tons of new dimensions!",
    "ClassId": 6,
    "Status": 4,
    "Links": {
      "WebsiteUrl": "https://www.curseforge.com/minecraft/mc-mods/hundred-one-dimensions",
      "WikiUrl": "",
      "IssuesUrl": null,
      "SourceUrl": "https://mcreator.net/modification/45963/101-dimensions"
    },
    "Categories": [
      {
        "Id": 410,
        "GameId": 432,
        "Name": "Dimensions",
        "Slug": "world-dimensions",
        "Url": "https://www.curseforge.com/minecraft/mc-mods/world-gen/world-dimensions",
        "IconUrl": "https://media.forgecdn.net/avatars/6/25/635351494468414756.png",
        "DateModified": "2014-05-08T17:37:26.84Z",
        "IsClass": false,
        "ClassId": 6,
        "ParentCategoryId": 406,
        "DisplayIndex": null
      },
      {
        "Id": 407,
        "GameId": 432,
        "Name": "Biomes",
        "Slug": "world-biomes",
        "Url": "https://www.curseforge.com/minecraft/mc-mods/world-gen/world-biomes",
        "IconUrl": "https://media.forgecdn.net/avatars/6/22/635351492995856506.png",
        "DateModified": "2014-05-08T17:34:59.587Z",
        "IsClass": false,
        "ClassId": 6,
        "ParentCategoryId": 406,
        "DisplayIndex": null
      }
    ],
    "Logo": {
      "Id": 286830,
      "ModId": 314924,
      "Title": "637305997654813298.png",
      "Description": "",
      "ThumbnailUrl": "https://media.forgecdn.net/avatars/thumbnails/286/830/256/256/637305997654813298.png",
      "Url": "https://media.forgecdn.net/avatars/286/830/637305997654813298.png"
    },
    "LatestFiles": [
      {
        "Id": 2676763,
        "GameId": 432,
        "ModId": 314924,
        "IsAvailable": true,
        "DisplayName": "101 Dimensions (1.12.2)",
        "FileName": "101 Dimensions (1.12.2) (3).jar",
        "FileStatus": 4,
        "FileDate": "2019-02-19T03:45:27.863Z",
        "FileLength": 1668797,
        "DownloadCount": 50366,
        "DownloadUrl": "https://edge.forgecdn.net/files/2676/763/101 Dimensions (1.12.2) (3).jar",
        "GameVersions": [
          "1.12.2"
        ],
        "Dependencies": []
      },
      {
        "Id": 3732389,
        "GameId": 432,
        "ModId": 314924,
        "IsAvailable": true,
        "DisplayName": "101 Dimensions 1.1.0 (1.16.5)",
        "FileName": "101 Dimensions 1.1.0 (1.16.5).jar",
        "FileStatus": 4,
        "FileDate": "2022-04-03T00:34:00.807Z",
        "FileLength": 1946105,
        "DownloadCount": 0,
        "DownloadUrl": "https://edge.forgecdn.net/files/3732/389/101 Dimensions 1.1.0 (1.16.5).jar",
        "GameVersions": [
          "1.16.3",
          "1.16.1",
          "1.16",
          "1.16.5",
          "Forge",
          "1.16.4",
          "1.16.2"
        ],
        "Dependencies": []
      }
    ],
    "DateCreated": "2019-02-19T00:40:41.71Z",
    "DateModified": "2022-04-03T00:40:52.95Z",
    "DateReleased": "2022-04-03T00:34:00.807Z",
    "GamePopularityRank": 12442,
    "DownloadCount": 84825,
    "IsAvailable": true,
    "Selected": true
  },
  {
    "Id": 474854,
    "GameId": 432,
    "Name": " 3rd life",
    "Slug": "third-life",
    "Summary": "Minecraft... but with 3 lives.",
    "ClassId": 6,
    "Status": 4,
    "Links": {
      "WebsiteUrl": "https://www.curseforge.com/minecraft/mc-mods/third-life",
      "WikiUrl": "",
      "IssuesUrl": null,
      "SourceUrl": null
    },
    "Categories": [
      {
        "Id": 424,
        "GameId": 432,
        "Name": "Cosmetic",
        "Slug": "cosmetic",
        "Url": "https://www.curseforge.com/minecraft/mc-mods/cosmetic",
        "IconUrl": "https://media.forgecdn.net/avatars/6/39/635351497555976928.png",
        "DateModified": "2014-05-08T17:42:35.597Z",
        "IsClass": false,
        "ClassId": 6,
        "ParentCategoryId": 6,
        "DisplayIndex": null
      },
      {
        "Id": 425,
        "GameId": 432,
        "Name": "Miscellaneous",
        "Slug": "mc-miscellaneous",
        "Url": "https://www.curseforge.com/minecraft/mc-mods/mc-miscellaneous",
        "IconUrl": "https://media.forgecdn.net/avatars/6/40/635351497693711265.png",
        "DateModified": "2014-06-15T04:27:14.543Z",
        "IsClass": false,
        "ClassId": 6,
        "ParentCategoryId": 6,
        "DisplayIndex": null
      },
      {
        "Id": 411,
        "GameId": 432,
        "Name": "Mobs",
        "Slug": "world-mobs",
        "Url": "https://www.curseforge.com/minecraft/mc-mods/world-gen/world-mobs",
        "IconUrl": "https://media.forgecdn.net/avatars/6/53/635351500195070414.png",
        "DateModified": "2014-05-08T17:46:59.507Z",
        "IsClass": false,
        "ClassId": 6,
        "ParentCategoryId": 406,
        "DisplayIndex": null
      }
    ],
    "Logo": {
      "Id": 374081,
      "ModId": 474854,
      "Title": "637547286710220320.gif",
      "Description": "",
      "ThumbnailUrl": "https://media.forgecdn.net/avatars/thumbnails/374/81/256/256/637547286710220320_animated.gif",
      "Url": "https://media.forgecdn.net/avatars/374/81/637547286710220320.gif"
    },
    "LatestFiles": [
      {
        "Id": 3405987,
        "GameId": 432,
        "ModId": 474854,
        "IsAvailable": true,
        "DisplayName": "3rd life (1.16.5) 1.0.4",
        "FileName": "3rd life (1.16.5) 1.0.4.jar",
        "FileStatus": 4,
        "FileDate": "2021-07-30T02:00:48.29Z",
        "FileLength": 82338,
        "DownloadCount": 5388,
        "DownloadUrl": "https://edge.forgecdn.net/files/3405/987/3rd life (1.16.5) 1.0.4.jar",
        "GameVersions": [
          "1.16.5",
          "Forge"
        ],
        "Dependencies": []
      }
    ],
    "DateCreated": "2021-04-22T22:51:10.97Z",
    "DateModified": "2021-07-30T02:01:51.23Z",
    "DateReleased": "2021-07-30T02:00:48.29Z",
    "GamePopularityRank": 11833,
    "DownloadCount": 25549,
    "IsAvailable": true,
    "Selected": true
  },
  {
    "Id": 495064,
    "GameId": 432,
    "Name": " 3rd life+ Extra Lives And More!",
    "Slug": "third-life-plus",
    "Summary": "Extra lives until you dies...",
    "ClassId": 6,
    "Status": 4,
    "Links": {
      "WebsiteUrl": "https://www.curseforge.com/minecraft/mc-mods/third-life-plus",
      "WikiUrl": "",
      "IssuesUrl": null,
      "SourceUrl": null
    },
    "Categories": [
      {
        "Id": 418,
        "GameId": 432,
        "Name": "Genetics",
        "Slug": "technology-genetics",
        "Url": "https://www.curseforge.com/minecraft/mc-mods/technology/technology-genetics",
        "IconUrl": "https://media.forgecdn.net/avatars/6/33/635351495921521214.png",
        "DateModified": "2014-05-08T17:39:52.153Z",
        "IsClass": false,
        "ClassId": 6,
        "ParentCategoryId": 412,
        "DisplayIndex": null
      },
      {
        "Id": 424,
        "GameId": 432,
        "Name": "Cosmetic",
        "Slug": "cosmetic",
        "Url": "https://www.curseforge.com/minecraft/mc-mods/cosmetic",
        "IconUrl": "https://media.forgecdn.net/avatars/6/39/635351497555976928.png",
        "DateModified": "2014-05-08T17:42:35.597Z",
        "IsClass": false,
        "ClassId": 6,
        "ParentCategoryId": 6,
        "DisplayIndex": null
      },
      {
        "Id": 419,
        "GameId": 432,
        "Name": "Magic",
        "Slug": "magic",
        "Url": "https://www.curseforge.com/minecraft/mc-mods/magic",
        "IconUrl": "https://media.forgecdn.net/avatars/6/34/635351496247862494.png",
        "DateModified": "2014-05-08T17:40:24.787Z",
        "IsClass": false,
        "ClassId": 6,
        "ParentCategoryId": 6,
        "DisplayIndex": null
      },
      {
        "Id": 422,
        "GameId": 432,
        "Name": "Adventure and RPG",
        "Slug": "adventure-rpg",
        "Url": "https://www.curseforge.com/minecraft/mc-mods/adventure-rpg",
        "IconUrl": "https://media.forgecdn.net/avatars/6/37/635351497295252123.png",
        "DateModified": "2014-05-08T17:42:09.54Z",
        "IsClass": false,
        "ClassId": 6,
        "ParentCategoryId": 6,
        "DisplayIndex": null
      },
      {
        "Id": 411,
        "GameId": 432,
        "Name": "Mobs",
        "Slug": "world-mobs",
        "Url": "https://www.curseforge.com/minecraft/mc-mods/world-gen/world-mobs",
        "IconUrl": "https://media.forgecdn.net/avatars/6/53/635351500195070414.png",
        "DateModified": "2014-05-08T17:46:59.507Z",
        "IsClass": false,
        "ClassId": 6,
        "ParentCategoryId": 406,
        "DisplayIndex": null
      }
    ],
    "Logo": {
      "Id": 399802,
      "ModId": 495064,
      "Title": "637604036469321603.gif",
      "Description": "",
      "ThumbnailUrl": "https://media.forgecdn.net/avatars/thumbnails/399/802/256/256/637604036469321603_animated.gif",
      "Url": "https://media.forgecdn.net/avatars/399/802/637604036469321603.gif"
    },
    "LatestFiles": [
      {
        "Id": 4103168,
        "GameId": 432,
        "ModId": 495064,
        "IsAvailable": true,
        "DisplayName": "(1.18.2) - 3rdLife+ - 1.0.6",
        "FileName": "3rdLife+(1.18.2) 1.0.6.jar",
        "FileStatus": 4,
        "FileDate": "2022-11-21T18:05:51.293Z",
        "FileLength": 160869,
        "DownloadCount": 0,
        "DownloadUrl": "https://edge.forgecdn.net/files/4103/168/3rdLife+(1.18.2) 1.0.6.jar",
        "GameVersions": [
          "1.18.2",
          "Forge"
        ],
        "Dependencies": []
      }
    ],
    "DateCreated": "2021-06-17T14:26:33.57Z",
    "DateModified": "2022-11-21T18:08:34.443Z",
    "DateReleased": "2022-11-21T18:05:51.293Z",
    "GamePopularityRank": 6299,
    "DownloadCount": 41128,
    "IsAvailable": true,
    "Selected": true
  },
  {
    "Id": 498704,
    "GameId": 432,
    "Name": " Bruno's craftable chainmail [FORGE]",
    "Slug": "bruno-s-craftable-chainmail",
    "Summary": "allows you to create chainmail armor",
    "ClassId": 6,
    "Status": 4,
    "Links": {
      "WebsiteUrl": "https://www.curseforge.com/minecraft/mc-mods/bruno-s-craftable-chainmail",
      "WikiUrl": "",
      "IssuesUrl": null,
      "SourceUrl": "https://drive.google.com/file/d/185YXzs7OKXO8jXG6f8DVB5kmLjXDMz5a/view?usp=sharing"
    },
    "Categories": [
      {
        "Id": 434,
        "GameId": 432,
        "Name": "Armor, Tools, and Weapons",
        "Slug": "armor-weapons-tools",
        "Url": "https://www.curseforge.com/minecraft/mc-mods/armor-weapons-tools",
        "IconUrl": "https://media.forgecdn.net/avatars/6/47/635351498790409758.png",
        "DateModified": "2014-05-08T17:44:39.057Z",
        "IsClass": false,
        "ClassId": 6,
        "ParentCategoryId": 6,
        "DisplayIndex": null
      },
      {
        "Id": 4906,
        "GameId": 432,
        "Name": "MCreator",
        "Slug": "mc-creator",
        "Url": "https://www.curseforge.com/minecraft/mc-mods/mc-creator",
        "IconUrl": "https://media.forgecdn.net/avatars/380/489/637562419922532076.png",
        "DateModified": "2021-05-10T11:13:12.27Z",
        "IsClass": false,
        "ClassId": 6,
        "ParentCategoryId": 6,
        "DisplayIndex": null
      }
    ],
    "Logo": {
      "Id": 400203,
      "ModId": 498704,
      "Title": "637604875149118676.png",
      "Description": "",
      "ThumbnailUrl": "https://media.forgecdn.net/avatars/thumbnails/400/203/256/256/637604875149118676.png",
      "Url": "https://media.forgecdn.net/avatars/400/203/637604875149118676.png"
    },
    "LatestFiles": [
      {
        "Id": 3367635,
        "GameId": 432,
        "ModId": 498704,
        "IsAvailable": true,
        "DisplayName": "craftable chainmail.jar",
        "FileName": "craftable chainmail.jar",
        "FileStatus": 4,
        "FileDate": "2021-06-28T14:35:49.207Z",
        "FileLength": 13086,
        "DownloadCount": 14,
        "DownloadUrl": "https://edge.forgecdn.net/files/3367/635/craftable chainmail.jar",
        "GameVersions": [
          "1.16.5"
        ],
        "Dependencies": []
      },
      {
        "Id": 3476334,
        "GameId": 432,
        "ModId": 498704,
        "IsAvailable": true,
        "DisplayName": "craftable chainmail 1.2.jar",
        "FileName": "craftable chainmail 1.2.jar",
        "FileStatus": 4,
        "FileDate": "2021-09-29T12:59:45.31Z",
        "FileLength": 16482,
        "DownloadCount": 974,
        "DownloadUrl": "https://edge.forgecdn.net/files/3476/334/craftable chainmail 1.2.jar",
        "GameVersions": [
          "1.16.5"
        ],
        "Dependencies": []
      }
    ],
    "DateCreated": "2021-06-28T14:31:54.86Z",
    "DateModified": "2021-09-29T13:01:13.947Z",
    "DateReleased": "2021-09-29T12:59:45.31Z",
    "GamePopularityRank": 38089,
    "DownloadCount": 1703,
    "IsAvailable": true,
    "Selected": true
  }
]